{
  "packageRules": [
    {
      "matchDatasources": ["docker"],
      "automerge": true,
      "automergeType": "branch",
      "requiredStatusChecks": null,
      "matchUpdateTypes": ["minor", "patch"],
      "matchPackageNames": [
        "ghcr.io/k8s-at-home/jackett",
        "ghcr.io/k8s-at-home/lidarr",
        "ghcr.io/k8s-at-home/plex",
        "ghcr.io/k8s-at-home/prowlarr",
        "ghcr.io/k8s-at-home/radarr-develop",
        "ghcr.io/k8s-at-home/readarr",
        "ghcr.io/k8s-at-home/sonarr-develop"
      ]
    },
    {
      "matchDatasources": ["docker"],
      "automerge": true,
      "automergeType": "branch",
      "requiredStatusChecks": null,
      "matchUpdateTypes": ["patch"],
      "matchPackageNames": [
        "ghcr.io/airsonic-advanced/airsonic-advanced",
        "quay.io/minio/minio"
      ]
    },
    {
      "matchDatasources": ["helm"],
      "automerge": true,
      "automergeType": "branch",
      "requiredStatusChecks": null,
      "matchUpdateTypes": ["minor", "patch"],
      "matchPackageNames": [
        "kube-prometheus-stack"
      ]
    },
    {
      "matchManagers": ["github-actions"],
      "automerge": true,
      "automergeType": "branch",
      "requiredStatusChecks": null,
      "matchUpdateTypes": ["minor", "patch"],
      "excludePackageNames": [
        "lycheeverse/lychee-action"
      ]
    }
    // Group packages
    {
      "matchDatasources": ["helm", "docker"],
      "matchPackagePatterns": ["^rook.ceph"],
      "groupName": "rook-ceph-suite",
      "additionalBranchPrefix": "",
      "separateMinorPatch": true,
    },
    {
      "matchDatasources": ["docker"],
      "matchPackageNames": [
        "k8s.gcr.io/kube-apiserver",
        "k8s.gcr.io/kube-controller-manager",
        "k8s.gcr.io/kube-scheduler",
        "ghcr.io/siderolabs/kubelet"
      ],
      "groupName": "kubernetes",
      "additionalBranchPrefix": "",
      "separateMinorPatch": true,
    },
    {
      "matchDatasources": ["helm", "docker"],
      "matchPackageNames": [
        "quay.io/cilium/cilium",
        "quay.io/cilium/operator-generic",
        "cilium",
      ],
      "groupName": "cilium",
      "additionalBranchPrefix": "",
      "separateMinorPatch": true,
    }
  ]
}
